<?xml version="1.0" encoding="UTF-8"?>
<TEXTE_JURI_JUDI>
<META>
<META_COMMUN>
<ID>JURITEXT000030205315</ID>
<ANCIEN_ID/>
<ORIGINE>JURI</ORIGINE>
<URL>texte/juri/judi/JURI/TEXT/00/00/30/20/53/JURITEXT000030205315.xml</URL>
<NATURE>ARRET</NATURE>
</META_COMMUN>
<META_SPEC>
<META_JURI>
<TITRE>Cour de cassation, civile, Chambre sociale, 4 février 2015, 13-20.879, Publié au bulletin</TITRE>
<DATE_DEC>2015-02-04</DATE_DEC>
<JURIDICTION>Cour de cassation</JURIDICTION>
<NUMERO>51500233</NUMERO>
<SOLUTION>Rejet</SOLUTION>
</META_JURI>
<META_JURI_JUDI>
<NUMEROS_AFFAIRES>
<NUMERO_AFFAIRE>13-20879</NUMERO_AFFAIRE>
</NUMEROS_AFFAIRES>
<PUBLI_BULL publie="oui"/>
<FORMATION>CHAMBRE_SOCIALE</FORMATION>

<FORM_DEC_ATT>Cour appel de Besançon</FORM_DEC_ATT>
<DATE_DEC_ATT>2013-05-14</DATE_DEC_ATT>
<SIEGE_APPEL/>
<JURI_PREM/>
<LIEU_PREM/>
<DEMANDEUR/>
<DEFENDEUR/>
<PRESIDENT>M. Frouin</PRESIDENT>
<AVOCAT_GL>M. Beau</AVOCAT_GL>
<AVOCATS>Me Blondel</AVOCATS>
<RAPPORTEUR>M. Mallard</RAPPORTEUR>
<ECLI>ECLI:FR:CCASS:2015:SO00233</ECLI>
</META_JURI_JUDI>
</META_SPEC>
</META>
<TEXTE>
<BLOC_TEXTUEL>
<CONTENU>
<p>LA COUR DE CASSATION, CHAMBRE SOCIALE, a rendu arrêt suivant : </p>
<p>Attendu, selon arrêt attaqué, (Besançon, 14 mai 2013), que M. X..., engagé le 1er octobre 2002 par la société Y...en qualité de soudeur, a saisi la juridiction pruhomale afin de se voir reconnaître la classification niveau III, position 1 coefficient 210 et obtenir un rappel de salaire au titre du salaire minimum conventionnel ; </p>
<p>Sur le premier moyen : </p>
<p>Attendu que employeur fait grief à arrêt accueillir la demande au titre de la classification, alors, selon le moyen, qu'il résulte de article 12. 2 de la convention collective nationale des ouvriers employés par les entreprises du bâtiment que les ouvriers de niveau III/ 1 sont responsables des travaux de leur métier et que ces travaux impliquent la lecture de plans et la tenue de documents exécution qui y rapportent ; qu'en espèce, pour dire que M. Lionel X...est fondé à revendiquer la classification ouvrier de niveau III/ 1, la cour appel énonce que la définition conventionnelle n'exige pas que le salarié en cause assure cumulativement la lecture de plans et la tenue de documents exécution ; qu'en statuant ainsi, la cour appel viole le texte précité ; </p>
<p>Mais attendu, que selon article 12-2 de la convention collective nationale des ouvriers employés par les entreprises du bâtiment, les ouvriers de niveau III/ 1 exécutent les travaux de leur métier, à partir de directives et sous contrôle de bonne fin et qu'ils sont responsables de la bonne réalisation de ces travaux qui peuvent impliquer la lecture de plans et la tenue de documents exécution qui y rapportent ; </p>
<p>Et attendu que ce texte ne visant la lecture de plans et la tenue de documents qu'à titre de simple possibilité, existence de un ou autre de ces éléments ne constitue pas une condition obtention de la classification ; </p>
<p>D'où il suit que le moyen n'est pas fondé ; </p>
<p>Sur le second moyen : </p>
<p>Attendu que employeur fait grief à arrêt de faire droit à la demande au titre du salaire minimum conventionnel, alors, selon le moyen : </p>
<p>1°/ qu'il résulte de article IV de la Convention collective nationale des employés et ouvriers des entreprises de bâtiment que la rémunération des ouvriers inclut les primes et indemnités relatives aux prestations qu'ils effectuent ; qu'une prime calculée en fonction de la production réalisée par un atelier, est, même si elle est perçue par tous les salariés, relative à la prestation effectuée par chacun eux de sorte qu'elle doit être prise en considération pour vérifier application du salaire minimum conventionnel ; qu'en décidant au contraire que le fait que la prime atelier ne soit pas exclusivement calculée en fonction du travail individuel de M. X...mais en fonction de la productivité de son atelier excluait sa prise en considération pour vérifier application du salaire minimum conventionnel, la cour appel viole le texte précité ensemble article 1134 du code civil ; </p>
<p>2°/ pour considérer en substance que la prime atelier est une prime assiduité « déguisée » destinée à pénaliser absentéisme et ainsi exclure sa prise en considération pour vérifier application du salaire minimum conventionnel, la cour appel se borne à retenir, nonobstant le versement constant de la prime de 2005 à 2009 lors des absences du salarié, que employeur n'a pas versé de prime atelier à M. X...pour les mois de juillet et septembre 2009, mois durant lesquels le salarié a été absent pour maladie ; qu'en se déterminant ainsi sur un défaut de paiement isolé, la cour appel ne justifie pas légalement sa décision au regard de article IV de la Convention collective nationale des employés et ouvriers des entreprises de bâtiment, ensemble article 1134 du code civil ; </p>
<p>Mais attendu, selon article 4. 11 de la convention collective nationale des employés et ouvriers des entreprises du bâtiment occupant plus de dix salariés, que le salaire mensuel constitue la rémunération des ouvriers du bâtiment pour tous les aspects de exercice normal et habituel de leur métier et que par conséquent, aucune prime ou indemnité conventionnelle ne leur est due, en sus du salaire mensuel pour les travaux qu'ils effectuent à ce titre ; que selon article 4. 13 de cette convention ajoutent, le cas échéant, au salaire mensuel diverses majorations, primes et indemnités prévues par les conventions collectives régionales applicables aux ouvriers ; qu'il en déduit que les primes qui ne rémunèrent pas le travail du salarié, mais qui sont liées à sa présence ou à son ancienneté dans entreprise, n'entrent pas dans le calcul du minimum conventionnel ; </p>
<p>Et attendu que la cour appel, qui a constaté que le salarié n'avait pas bénéficié de la prime atelier pendant les mois de juillet, août et septembre 2009, alors qu'il avait été absent durant une partie de ces mois, en a exactement déduit que cette prime était liée à la présence du salarié et ne pouvait être prise en compte pour vérifier si le minimum conventionnel avait été respecté ; </p>
<p>D'où il suit que le moyen n'est pas fondé ; </p>
<p>PAR CES MOTIFS : </p>
<p>REJETTE le pourvoi ; </p>
<p>Condamne la société Y...aux dépens ; </p>
<p>Ainsi fait et jugé par la Cour de cassation, chambre sociale, et prononcé par le président en son audience publique du quatre février deux mille quinze. </p>

<p>MOYENS ANNEXES au présent arrêt </p>
<p>Moyens produits par Me Blondel, avocat aux Conseils, pour la société Y.... </p>
<p>PREMIER MOYEN DE CASSATION </p>
<p>Il est reproché à arrêt infirmatif attaqué avoir dit que Monsieur Lionel X...est fondé à prétendre à une reclassification au niveau III position 1 coefficient 2010 à compter du 1er septembre 2010 et avoir, en conséquence, condamné la société Y...à payer à Monsieur Y...un rappel de salaire et de congés payés respectivement un montant de 3 878, 60 € et 387, 86 € et dit que la société Y...devait procéder à la régularisation des salaires dus à Monsieur X...à compter du 1er octobre 2010 sur la base du salaire minimum conventionnel afférent au coefficient 2010, prime atelier incluse ; </p>
<p>AUX MOTIFS QU'il convient de relever liminairement que Monsieur Lionel X...a été classé lors de son embauche au niveau II coefficient 185, soit au niveau minimum prévu par article 12-41 de la convention collective applicable concernant les salariés titulaires un CAP ou un BEP, et qu'il n'a bénéficié aucune évolution de sa carrière professionnelle, en dépit une ancienneté de services de plus de huit ans lui conférant une expérience professionnelle certaine ; que contrairement à ce que soutient la société intimée, celle-ci avait bien obligation à issue une période maximale de neuf mois après embauche, de réexaminer la situation de Monsieur Lionel X...et de lui notifier expressément il était reconnu dans sa position initiale ou classée à un niveau supérieur en fonction de ses aptitudes et capacités professionnelles ; qu'en espèce, intimée n'a à aucun moment, avant la réclamation écrite formulée par Monsieur Lionel X...le 30 août 2010 à la suite de demandes orales demeurées infructueuses, estimé nécessaire de procéder à un réexamen de la classification de celui-ci ; que sa réponse en date du 7 septembre 2010 ne satisfait en aucune façon à obligation un réexamen de la classification en fonction des aptitudes et capacités professionnelles du salarié, puisqu'elle se borne à rappeler le niveau accueil du titulaire un BEP et à signaler que ce sont les emplois qui sont classés et non pas les salariés pris individuellement, ce qui n'est pas exact ; que pour autant, la juridiction ne saurait sanctionner le non-respect de cette obligation par un positionnement du salarié emblée au niveau supérieur (niveau III-position 1- coefficient 210) à expiration du délai de 9 mois, sans vérifier que dès ce moment là Monsieur Lionel X...était en mesure exécuter les travaux de son métier de soudeur dans les conditions prescrites par les dispositions conventionnelles (article 12-2) à savoir : « les ouvriers de niveau III/ 1 exécutent les travaux de leur métier, à partir de directives et sous contrôle de bonne fin. Ils sont responsables de la bonne réalisation de ces travaux qui peuvent impliquer la lecture de plans et la tenue de documents exécution qui y rapportent. Dans exécution de ces tâches, ils peuvent :- être assistés autres ouvriers, en principe de qualification moindre, qui les aident dans accomplissement de leurs tâches et dont ils guident le travail,- être amenés ponctuellement, sur instructions de encadrement, à assumer des fonctions de représentation simple ayant trait à exécution de leur travail quotidien et à transmettre leur expérience, notamment à des apprentis ou à des nouveaux embauchés. Ils possèdent et mettent en oeuvre de bonnes connaissances professionnelles acquises par formation professionnelle, initiale ou continue, ou une expérience équivalente » ; que les attestations et documents techniques produits aux débats par les parties établissent :- que Monsieur Lionel X...exerçait les fonctions de soudeur-pointeur (attestation Léon B...) qui comportent des opérations plus complexes que celles de soudeur, en ce qu'elles impliquent de sa part la lecture de plans assemblage et la définition des points de soudure à réaliser à partir desdits plans et de la liste des composants ;- qu'il effectuait des travaux de soudure avec des intérimaires travaillant sous ses directives (attestations de Jean Z...et de Cédric A...) ; qu'il apparaît donc qu'il remplissait bien les conditions exigées pour être classé au niveau III position 1 coefficient 210 à la date introduction de la demande, et ce nonobstant les déclarations de Monsieur Léon B..., chef atelier, indiquant qu'il distribuait le travail à accomplir, donnait les directives et assurait la tenue des documents techniques ; que le fait de distribuer le travail aux différentes équipes de atelier et de donner des directives n'exclut pas qu'au sein de chaque équipe, un soudeur expérimenté guide le travail intérimaires et leur donne des directives exécution ; que de même la définition conventionnelle n'exige pas que le salarié en cause assure cumulativement la lecture de plans et la tenue de documents exécution ; que appelant n'établit pas toutefois que les fonctions de soudeur-pointeur lui aient été confiées dès 2003, et qu'il ait été amené à encadrer le travail intérimaires et à transmettre son expérience à ceux-ci avant année 2010 ; qu'il convient en conséquence infirmer partiellement le jugement déféré et de faire droit à la demande de classification au niveau III position 1 coefficient 210, à effet du 1er septembre 2010 et aux rappels de salaires sur la base du minimum conventionnel afférent à celui-ci ; </p>
<p>ET AUX MOTIFS ENCORE QUE le montant du rappel de salaires dû, sur la base du coefficient 185 octobre 2005 à août 2010, prime ancienneté et prime atelier exclues du calcul du minimum conventionnel, établit donc selon le décompte et les bulletins de salaire communiqués aux débats par Monsieur Lionel X...à la somme de 3 590, 84 € ; que le montant du rappel de salaire dû pour le mois de septembre 2010 sur la base du coefficient 2010, calculé dans les mêmes conditions, établit à la somme de 287, 76 € soit un rappel de salaires octobre 2005 à septembre 2010 de 3 878, 60 € brut outre congés payés afférents ; qu'il incombera à la société Y...de procéder à la régularisation des salaires dus à compter octobre 2010, conformément aux dispositions du présent arrêt ; </p>
<p>ALORS QU'il résulte de article 12. 2 de la convention collective nationale des ouvriers employés par les entreprises du bâtiment que les ouvriers de niveau III/ 1 sont responsables des travaux de leur métier et que ces travaux impliquent la lecture de plans et la tenue de documents exécution qui y rapportent ; qu'en espèce, pour dire que Monsieur Lionel X...est fondé à revendiquer la classification ouvrier de niveau III/ 1, la Cour énonce que la définition conventionnelle n'exige pas que le salarié en cause assure cumulativement la lecture de plans et la tenue de documents exécution ; qu'en statuant ainsi, la Cour viole le texte précité. </p>
<p>SECOND MOYEN DE CASSATION </p>
<p>Il est reproché à arrêt infirmatif attaqué avoir dit que la prime atelier versée par la société Y...à Monsieur Lionel X...ne doit pas être pris en compte dans le calcul du salaire minimum conventionnel et avoir, en conséquence, condamné la société Y...à payer à Monsieur Y...un rappel de salaire et de congés payés respectivement un montant de 3 878, 60 € et 387, 86 € et dit que la société Y...devait procéder à la régularisation des salaires dus à Monsieur X...à compter du 1er octobre 2010 sur la base du salaire minimum conventionnel afférent au coefficient 2010, prime atelier incluse ; </p>
<p>AUX MOTIFS QU'en absence de dispositions spécifiques dans la convention collective des ouvriers du bâtiment applicable à entreprise concernant les éléments de rémunération à prendre en compte pour vérifier si le salaire minimum conventionnel a été versé aux salariés, les premiers juges se sont référés à juste titre aux principes dégagés par la jurisprudence, selon lesquels seules peuvent être prises en compte les primes qui sont la contrepartie directe de la prestation de travail du salarié, à exclusion de celles qui sont liées à la présence ou à ancienneté de celui-ci dans entreprise ; qu'il est constant que la prime ancienneté doit être exclue ; que agissant de la prime atelier les premiers juges ont retenu qu'il agissait une prime de production liée au tonnage produit par atelier rapporté au nombre heures effectuées, et donc une prime directement liée à exécution de la prestation de travail ; que Monsieur Lionel X...indique qu'il agit une prime collective, liée à la présence du salarié dans entreprise, dans la mesure où il a été privé du bénéfice de celle-ci lors de ses absences pour maladie en juillet - août et septembre 2009 ; que de fait, le calcul de la prime n'est pas directement lié au travail individuel fourni par le salarié, mais à la productivité de atelier, le montant de celle-ci étant fixé en pourcentage du salaire variable chaque mois en fonction du tonnage moyen réalisé par heure effectuée, le taux étant identique pour tous les salariés et sans lien direct avec la prestation de travail de chacun eux ; qu'il résulte de plus des bulletins de salaire produits par appelant que celui-ci n'a perçu aucune prime atelier pendant les mois de juillet, août et septembre 2009, alors que la production réalisée donnait droit à une prime atelier de :- juillet 4 %,- août 0 %,- septembre 11, 25 % et que Monsieur Lionel X...n'a pas été absent pour maladie pendant la totalité de la période en cause mais seulement 105 heures en juillet et 61, 50 heures en septembre 2009 ; que le fait qu'il n'ait pas bénéficié de la prime au prorata de son temps de travail ces deux mois démontre que celle-ci est bien liée à la présence du salarié et à son assiduité et vise à pénaliser absentéisme ; que le fait qu'elle soit versée en cas absence pour congés payés ne contredit pas cette évidence, étant donné que les périodes de congés payés sont assimilées par la loi à des périodes de travail effectif et sont une durée proportionnelle au temps de travail ; que les primes atelier ne peuvent donc être prises en compte pour vérifier si le minimum conventionnel a été respecté ; </p>
<p>ET AUX MOTIFS ENCORE QUE le montant du rappel de salaires dû, sur la base du coefficient 185 octobre 2005 à août 2010, prime ancienneté et prime atelier exclues du calcul du minimum conventionnel, établit donc selon le décompte et les bulletins de salaire communiqués aux débats par Monsieur Lionel X...à la somme de 3 590, 84 € ; que le montant du rappel de salaire dû pour le mois de septembre 2010 sur la base du coefficient 2010, calculé dans les mêmes conditions, établit à la somme de 287, 76 € soit un rappel de salaires octobre 2005 à septembre 2010 de 3 878, 60 € brut outre congés payés afférents ; qu'il incombera à la société Y...de procéder à la régularisation des salaires dus à compter octobre 2010, conformément aux dispositions du présent arrêt ; </p>
<p>ALORS QUE, D'UNE PART, il résulte de article IV de la Convention collective nationale des employés et ouvriers des entreprises de bâtiment que la rémunération des ouvriers inclut les primes et indemnités relatives aux prestations qu'ils effectuent ; qu'une prime calculée en fonction de la production réalisée par un atelier, est, même si elle est perçue par tous les salariés, relative à la prestation effectuée par chacun eux de sorte qu'elle doit être prise en considération pour vérifier application du salaire minimum conventionnel ; qu'en décidant au contraire que le fait que la prime atelier ne soit pas exclusivement calculée en fonction du travail individuel de Monsieur X...mais en fonction de la productivité de son atelier excluait sa prise en considération pour vérifier application du salaire minimum conventionnel, la Cour viole le texte précité ensemble article 1134 du Code civil ; </p>
<p>ALORS QUE, D'AUTRE PART, pour considérer en substance que la prime atelier est une prime assiduité « déguisée » destinée à pénaliser absentéisme et ainsi exclure sa prise en considération pour vérifier application du salaire minimum conventionnel, la Cour se borne à retenir, nonobstant le versement constant de la prime de 2005 à 2009 lors des absences du salarié, que employeur n'a pas versé de prime atelier à Monsieur X...pour les mois de juillet et septembre 2009, mois durant lesquels le salarié a été absent pour maladie ; qu'en se déterminant ainsi sur un défaut de paiement isolé, la Cour ne justifie pas légalement sa décision au regard de article IV de la Convention collective nationale des employés et ouvriers des entreprises de bâtiment, ensemble article 1134 du Code civil.</p>

</CONTENU>
</BLOC_TEXTUEL>
<SOMMAIRE>
<SCT ID="1" TYPE="PRINCIPAL">STATUT COLLECTIF DU TRAVAIL - Conventions et accords collectifs -  Conventions diverses -  Bâtiment -  Convention collective nationale des ouvriers employés par les entreprises du bâtiment non visées par le décret du 1er mars 1962 (est-à-dire occupant plus de 10 salariés) du 8 octobre 1990 -  Article 12.2 -  Grille de classification -  Classification III/1 -  Conditions -  Détermination -  Portée
</SCT>
<SCT ID="1" TYPE="REFERENCE"/>
<ANA ID="1">L'article 12.2 de la convention collective nationale des ouvriers employés par les entreprises du bâtiment occupant plus de 10 salariés, ne visant la lecture de plans et la tenue de documents qu'à titre de simple possibilité, existence de un ou autre de ces éléments ne constitue pas une condition obtention de la classification III/1</ANA>
<SCT ID="2" TYPE="PRINCIPAL">STATUT COLLECTIF DU TRAVAIL - Conventions et accords collectifs -  Conventions diverses -  Bâtiment -  Convention collective nationale des ouvriers employés par les entreprises du bâtiment non visées par le décret du 1er mars 1962 (est-à-dire occupant plus de 10 salariés) du 8 octobre 1990 -  Article 4.11. -  Salaire -  Salaire minimum conventionnel -  Eléments -  Prime -  Nature -  Détermination -  Portée
</SCT>
<SCT ID="2" TYPE="REFERENCE"/>
<ANA ID="2">Selon article 4.11. de la convention collective nationale des ouvriers employés par les entreprises du bâtiment occupant plus de 10 salariés, les primes qui ne rémunèrent pas le travail du salarié, mais qui sont liées à sa présence ou à son ancienneté dans entreprise, n'entrent pas dans le calcul du minimum conventionnel.
Justifie sa décision la cour appel qui, après avoir constaté que le salarié n'avait pas bénéficié de la prime atelier pendant les mois de juillet, août et septembre 2009, alors qu'il avait été absent durant une partie de ces mois, en déduit que cette prime était liée à la présence du salarié et ne pouvait être prise en compte pour vérifier si le minimum conventionnel avait été respecté</ANA>
</SOMMAIRE>

<CITATION_JP>
<CONTENU>Sur le n° 1 : Sur application de la procédure conventionnelle de classification des ouvriers employés par les entreprises du bâtiment, à rapprocher :Soc., 10 mars 1998, pourvoi n° 95-40.982, Bull. 1998, V, n° 127 (2) (cassation partielle).
Sur le n° 2 : Sur la détermination de primes exclues du calcul du salaire minimum conventionnel des ouvriers employés par les entreprises du bâtiment, dans le même sens que :Soc., 27 octobre 1999, pourvoi n° 98-44.627, Bull. 1999, V, n° 420 (1) (rejet), et arrêt cité



</CONTENU>
</CITATION_JP>
</TEXTE>
<LIENS>
<LIEN cidtexte="" datesignatexte="" id="" naturetexte="" nortexte="" num="" numtexte="" sens="source" typelien="CITATION">Sur le numéro 1 : article 12.2 de la convention collective nationale des ouvriers employés par les entreprises du bâtiment non visées par le décret du 1er mars 1962 (est-à-dire occupant plus de 10 salariés) du 8 octobre 1990</LIEN>
<LIEN cidtexte="" datesignatexte="" id="" naturetexte="" nortexte="" num="" numtexte="" sens="source" typelien="CITATION">Sur le numéro 2 : article 4.11. de la convention collective nationale des ouvriers employés par les entreprises du bâtiment non visées par le décret du 1er mars 1962 (est-à-dire occupant plus de 10 salariés) du 8 octobre 1990.</LIEN>
</LIENS>
</TEXTE_JURI_JUDI>
