<?xml version="1.0" encoding="UTF-8"?>
<TEXTE_JURI_JUDI>
<META>
<META_COMMUN>
<ID>JURITEXT000030266130</ID>
<ANCIEN_ID/>
<ORIGINE>JURI</ORIGINE>
<URL>texte/juri/judi/JURI/TEXT/00/00/30/26/61/JURITEXT000030266130.xml</URL>
<NATURE>ARRET</NATURE>
</META_COMMUN>
<META_SPEC>
<META_JURI>
<TITRE>Cour de cassation, civile, Chambre civile 1, 18 février 2015, 11-11.054, Publié au bulletin</TITRE>
<DATE_DEC>2015-02-18</DATE_DEC>
<JURIDICTION>Cour de cassation</JURIDICTION>
<NUMERO>11500304</NUMERO>
<SOLUTION>Rejet</SOLUTION>
</META_JURI>
<META_JURI_JUDI>
<NUMEROS_AFFAIRES>
<NUMERO_AFFAIRE>11-11054</NUMERO_AFFAIRE>
</NUMEROS_AFFAIRES>
<PUBLI_BULL publie="oui"/>
<FORMATION>CHAMBRE_CIVILE_1</FORMATION>

<FORM_DEC_ATT>Cour appel de Paris</FORM_DEC_ATT>
<DATE_DEC_ATT>2010-10-15</DATE_DEC_ATT>
<SIEGE_APPEL/>
<JURI_PREM/>
<LIEU_PREM/>
<DEMANDEUR/>
<DEFENDEUR/>
<PRESIDENT>Mme Batut</PRESIDENT>
<AVOCAT_GL>M. Ingall-Montagnier (premier avocat général)</AVOCAT_GL>
<AVOCATS>SCP Piwnica et Molinié</AVOCATS>
<RAPPORTEUR>Mme Canas</RAPPORTEUR>
<ECLI>ECLI:FR:CCASS:2015:C100304</ECLI>
</META_JURI_JUDI>
</META_SPEC>
</META>
<TEXTE>
<BLOC_TEXTUEL>
<CONTENU>
<p>LA COUR DE CASSATION, PREMIÈRE CHAMBRE CIVILE, a rendu arrêt suivant : </p>
<p>Donne acte à la société Emi Music France de ce qu'elle se désiste de son pourvoi et à la société Culture Press de ce qu'elle se désiste de son pourvoi en ce qu'il est dirigé contre la société Daniels and Partners ; </p>
<p>Attendu, selon arrêt attaqué (Paris, 15 octobre 2010), que soutenant être titulaires des droits artistes-interprètes et/ ou de producteurs sur divers enregistrements, fixés en Jamaïque entre 1964 et 1985, M. D... 
X... né E..., dit Jimmy Y..., M. Z..., dit Dennis A..., M. B..., dit F..., et M. C...ont assigné en contrefaçon les sociétés Culture Press et Emi Music France, leur reprochant avoir commercialisé en France, sans leur autorisation, plusieurs phonogrammes reproduisant ces enregistrements ; </p>
<p>Sur le premier moyen : </p>
<p>Attendu que la société Culture Press fait grief à arrêt de faire application de la loi française, de dire que la fabrication et la commercialisation en France des phonogrammes litigieux caractérisent une atteinte aux droits artistes-interprètes et, le cas échéant, de producteurs de MM. D... 
X..., Z..., B... et C..., de la condamner à réparation à leur profit et à garantie au profit de la société Emi Music France et de prononcer diverses mesures injonction et interdiction, alors, selon le moyen : </p>
<p>1°/ que article 19 du Copyright Act de 1911 dispose que « la personne qui est propriétaire des bandes mères à la date où elles ont été réalisées sera considérée comme étant le titulaire des droits » ; qu'en affirmant qu'il ne pouvait être déduit de la généralité des termes de ce texte que le propriétaire des bandes mères était initialement investi de ensemble des droits voisins du droit auteur sur les enregistrements dont elles constituaient le support, la cour appel a dénaturé le droit étranger applicable, violant article 3 du code civil, ensemble le texte précité ; </p>
<p>2°/ qu'en retenant en outre, pour contester que les propriétaires des bandes mères aient pu être investis à titre originaire de ensemble des droits voisins sur les prestations qui y trouvaient fixées, que les artistes-interprètes revendiquaient la qualité de coproducteurs de certains des enregistrements en litige et que cette qualité leur avait été reconnue par les premiers juges, la cour appel, qui a statué par un motif inopérant, a de nouveau violé article 3 du code civil, ensemble article 19 du Copyright Act de 1911 ; </p>
<p>3°/ qu'il incombe au juge français qui reconnaît applicable un droit étranger en rechercher, soit office, soit à la demande une partie qui invoque, la teneur, avec le concours des parties et personnellement il y a lieu, et de donner à la question litigieuse une solution conforme au droit positif étranger ; que la cour appel, qui a admis que le Copyright Act de 1911 était applicable au litige, a néanmoins retenu, pour évincer au profit de article L. 212-3 du code de la propriété intellectuelle, que ses dispositions étaient équivoques ; qu'en statuant ainsi, la cour appel a méconnu son office et violé article 3 du code civil ; </p>
<p>4°/ que la Convention de Rome du 26 octobre 1961 prévoit, en son article 20, qu'elle ne porte pas atteinte aux droits acquis dans un Etat contractant avant qu'elle n'y entre en vigueur ; qu'il en déduit qu'elle n'a pu remettre en cause ni les droits des producteurs origine sur les prestations fixées en Jamaïque avant le 27 janvier 1994, ni la validité des chaînes de contrats subséquentes ; qu'en affirmant que les sociétés Culture Press et Emi Music France, qui tenaient leurs droits utilisation des producteurs origine des prestations litigieuses, enregistrées en Jamaïque entre 1964 et 1985, auraient néanmoins dû solliciter autorisation de Jimmy Y..., Dennis A..., F... et Boris C..., en application du principe conventionnel du traitement national, la cour appel a violé le texte précité par refus application ; </p>
<p>5°/ que les effets des contrats conclus antérieurement à une loi nouvelle dépourvue effet rétroactif demeurent régis par les dispositions antérieures, même ils continuent à se réaliser postérieurement ; que autorisation utiliser la prestation un artiste-interprète régulièrement obtenue avant entrée en vigueur de article L. 212-3 du code de la propriété intellectuelle continue à produire ses effets après le 1er janvier 1986, sans que la poursuite de exploitation soit subordonnée à la délivrance une nouvelle autorisation écrite de artiste-interprète ; que les sociétés Culture Press et Emi Music France, qui tiennent leurs droits utilisation des producteurs origine, régulièrement investis, avant le 1er janvier 1986, de ensemble des droits de propriété intellectuelle sur les enregistrements litigieux, n'avaient pas à solliciter autorisation écrite des artistes-interprètes ; qu'en décidant du contraire, la cour appel a violé article 2 du code civil, ensemble le texte précité par fausse application et le principe de sécurité juridique qui découle de article 6 § 1 de la Convention de sauvegarde des droits de homme et des libertés fondamentales ; </p>
<p>Mais attendu que la règle de conflit de lois applicable à la détermination du titulaire initial des droits artiste-interprète et de producteur de phonogrammes désigne la loi du pays où la protection est réclamée ; que la cour appel a relevé qu'elle était saisie des atteintes qui auraient été portées, à compter de novembre 1996, aux droits de MM. D... 
X..., Z..., B... et C...du fait de la fabrication et de la commercialisation, en France, des enregistrements litigieux ; qu'il en résulte que, suivant la règle de conflit applicable, le litige est soumis à la loi française ; que par ce motif de pur droit, substitué à ceux critiqués dans les conditions de article 1015 du code de procédure civile, la décision déférée se trouve légalement justifiée ; </p>
<p>Sur le second moyen : </p>
<p>Attendu que la société Culture Press fait grief à arrêt de la condamner aux dépens de première instance et appel et au paiement de frais irrépétibles au profit de M. C..., alors, selon le moyen, que la partie perdante est condamnée aux dépens, à moins que le juge, par décision motivée, n'en mette la totalité ou une fraction à la charge une autre partie ; que le juge condamne la partie tenue aux dépens ou, à défaut, la partie perdante, à payer à autre partie la somme qu'il détermine, au titre des frais exposés et non compris dans les dépens ; qu'il en déduit que la condamnation de la partie qui n'a pas succombé aux dépens et au paiement des frais irrépétibles doit être assortie une motivation spéciale ; qu'en condamnant la société Culture Press, au profit de M. C..., aux dépens et frais irrépétibles de première instance et appel, sans assortir sa décision une motivation spéciale, bien que M. C...ait été débouté de toutes ses demandes à encontre de la société Culture Press, la cour appel a violé les articles 696 et 700 du code de procédure civile ; </p>
<p>Mais attendu que la société Culture Press n'a pas obtenu la condamnation qu'elle réclamait, à encontre de M. C..., sur le fondement de article 700 du code de procédure civile ; que, dès lors qu'elle succombait partiellement en ses prétentions, la cour appel n'a fait qu'user de son pouvoir discrétionnaire en mettant à sa charge les dépens ainsi qu'une indemnité au titre des frais irrépétibles ; que le moyen n'est pas fondé ; </p>
<p>PAR CES MOTIFS : </p>
<p>REJETTE le pourvoi ; </p>
<p>Condamne la société Culture Press aux dépens ; </p>
<p>Vu article 700 du code de procédure civile, rejette sa demande ; </p>
<p>Ainsi fait et jugé par la Cour de cassation, première chambre civile, et prononcé par le président en son audience publique du dix-huit février deux mille quinze. </p>

<p>MOYENS ANNEXES au présent arrêt </p>
<p>Moyens produits par la SCP Piwnica et Molinié, avocat aux Conseils, pour la société Culture Press </p>
<p>PREMIER MOYEN DE CASSATION </p>
<p>Il est fait grief à arrêt attaqué avoir infirmé le jugement entrepris en ce qui concerne la détermination de la loi applicable, avoir dit que la fabrication et la commercialisation en France des phonogrammes en litige reproduisant, sans leur autorisation, les interprétations de Jimmy Y..., F..., Dennis A... et Boris C...caractérisaient une atteinte à leurs droits artistes-interprètes et, le cas échéant, de producteurs, avoir condamné la société Culture Press à réparation à leur profit et à garantie au profit de la société Emi Music France et avoir prononcé diverses mesures injonction et interdiction, </p>
<p>AUX MOTIFS QU'il est constant que tous les enregistrements en cause ont été fixés pour la première fois en Jamaïque entre 1964 et 1985 ; que la société Culture Press et la société Emi Music France soulignent qu'à cette période, la loi jamaïcaine applicable était le Copyright Act de 1911 dont article 19 disposait que : « le copyright sur les enregistrements ¿ sera de cinquante années et ¿ la personne qui est propriétaire des bandes mères à la date où elles ont été réalisées sera considérée comme étant le titulaire des droits » ; que la cession des droits des artistes-interprètes au bénéfice du producteur n'était dès lors pas subordonnée à établissement un contrat de cession ; qu'elles ajoutent que la Convention de Rome entrée en vigueur en Jamaïque le 27 janvier 1994 impose (article 20) « le respect des droits acquis dans un quelconque des Etats contractants antérieurement à entrée en vigueur pour cet Etat de la Convention... » ; que, bien plus, lors de son entrée en vigueur, le Copyright Act de 1993 qui a succédé à celui de 1911, énonce : « Si, au jour entrée en vigueur désigné, des droits de copyright subsistent en vertu de article 19 du Copyright Act de 1911... ces droits de copyright continueront avoir la même étendue et les mêmes effets que ceux qu'ils auraient eus si la présente loi n'avait pas été votée » ; que les sociétés Culture Press et Emi Music France en déduisent que les producteurs origine des enregistrements en cause, titulaires des droits exploitation, selon le Copyright Act de 1911, les ont ainsi régulièrement cédés et/ ou licenciés à la société Culture Press ; mais qu'il peut difficilement être déduit de la généraIité des termes de article 19 du Copyright Act de 1911- selon la traduction produite-, que le propriétaire des bandes mères fût, du fait même de leur détention à époque où elles furent réalisées, titulaire de tous droits nés ou à naître et plus spécialement des droits voisins, sans avoir à justifier de accord des artistes ; qu'en espèce, plusieurs des intimés revendiquent ailleurs la qualité de co-producteurs de certains enregistrements, qualité reconnue par les premiers juges qui fait obstacle à la reconnaissance une présomption de titularité de tous droits exploitation liée à la seule détention originaire des bandes mères ; que la cour est saisie des atteintes qui auraient été portées, à compter de novembre 1996, aux droits des intimés du fait de la fabrication et de la commercialisation en France des enregistrements litigieux ; que les actes incriminés sont donc intervenus postérieurement à entrée en vigueur des textes conventionnel-Convention de Rome-et législatif-loi du 3 juillet 1985- dont les appelantes revendiquent le bénéfice ; que la France et la Jamaïque sont signataires de la Convention de Rome qui érige en principe, en son article 4, que chaque Etat accordera le bénéfice du traitement national aux ressortissants des autres Etats signataires ; que, si les dispositions nouvelles n'ont en effet pas vocation à rétroagir comme le prévoit article 20. 2 de la Convention de Rome, en revanche, elles ont vocation à régir appréciation des atteintes éventuellement portées aux droits des artistes-interprètes en raison actes de reproduction et de commercialisation commis, comme en espèce, postérieurement à entrée en vigueur de celle-ci ; qu'il suit que les intimés sont bien fondés à solliciter le bénéfice de la protection de la loi française du 3 juillet 1985 qui énonce que la reproduction et la communication au public de enregistrement de la prestation de artiste-interprète sont soumises à autorisation écrite de ce dernier (article L. 212-3 du code de la propriété intellectuelle) ; que la société Culture Press ne peut donc se limiter à alléguer qu'elle viendrait aux droits du propriétaire initial des bandes mères pour prétendre être investie du droit exploiter les enregistrements incriminés ; qu'en fabriquant et en commercialisant en France, après le 22 novembre 1996, des CD, sans avoir recueilli, comme précisé ci-après, accord des intimés, elle a porté atteinte aux droits voisins dont ceux-ci sont respectivement investis ; </p>
<p>1°/ ALORS QUE article 19 du Copyright Act de 1911 dispose que « la personne qui est propriétaire des bandes mères à la date où elles ont été réalisées sera considérée comme étant le titulaire des droits » ; qu'en affirmant qu'il ne pouvait être déduit de la généralité des termes de ce texte que le propriétaire des bandes mères était initialement investi de ensemble des droits voisins du droit auteur sur les enregistrements dont elles constituaient le support, la cour appel a dénaturé le droit étranger applicable, violant article 3 du code civil, ensemble le texte précité ; </p>
<p>2°/ ALORS QU'en retenant en outre, pour contester que les propriétaires des bandes mères aient pu être investis à titre originaire de ensemble des droits voisins sur les prestations qui y trouvaient fixées, que les artistes-interprètes revendiquaient la qualité de coproducteurs de certains des enregistrements en litige et que cette qualité leur avait été reconnue par les premiers juges, la cour appel, qui a statué par un motif inopérant, a de nouveau violé article 3 du code civil, ensemble article 19 du Copyright Act de 1911 ; </p>
<p>3°/ ALORS QU'en toute hypothèse, il incombe au juge français qui reconnaît applicable un droit étranger en rechercher, soit office, soit à la demande une partie qui invoque, la teneur, avec le concours des parties et personnellement il y a lieu, et de donner à la question litigieuse une solution conforme au droit positif étranger ; que la cour appel, qui a admis que le Copyright Act de 1911 était applicable au litige, a néanmoins retenu, pour évincer au profit de article L. 212-3 du code de la propriété intellectuelle, que ses dispositions étaient équivoques ; qu'en statuant ainsi, la cour appel a méconnu son office et violé article 3 du code civil ; </p>
<p>4°/ ALORS QUE la Convention de Rome du 26 octobre 1961 prévoit, en son article 20, qu'elle ne porte pas atteinte aux droits acquis dans un Etat contractant avant qu'elle n'y entre en vigueur ; qu'il en déduit qu'elle n'a pu remettre en cause ni les droits des producteurs origine sur les prestations fixées en Jamaïque avant le 27 janvier 1994, ni la validité des chaînes de contrats subséquentes ; qu'en affirmant que les sociétés Culture Press et Emi Music France, qui tenaient leurs droits utilisation des producteurs origine des prestations litigieuses, enregistrées en Jamaïque entre 1964 et 1985, auraient néanmoins dû solliciter autorisation de Jimmy Y..., Dennis A..., F... et Boris C..., en application du principe conventionnel du traitement national, la cour appel a violé le texte précité par refus application ; </p>
<p>5°/ ALORS QU'en toute hypothèse, les effets des contrats conclus antérieurement à une loi nouvelle dépourvue effet rétroactif demeurent régis par les dispositions antérieures, même ils continuent à se réaliser postérieurement ; que autorisation utiliser la prestation un artiste-interprète régulièrement obtenue avant entrée en vigueur de article L. 212-3 du code de la propriété intellectuelle continue à produire ses effets après 1er janvier 1986, sans que la poursuite de exploitation soit subordonnée à la délivrance une nouvelle autorisation écrite de artiste-interprète ; que les sociétés Culture Press et Emi Music France, qui tiennent leurs droits utilisation des producteurs origine, régulièrement investis, avant le 1er janvier 1986, de ensemble des droits de propriété intellectuelle sur les enregistrements litigieux, n'avaient pas à solliciter autorisation écrite des artistes-interprètes ; qu'en décidant du contraire, la cour appel a violé article 2 du code civil, ensemble le texte précité par fausse application et le principe de sécurité juridique qui découle de article 6 § 1 de la Convention de sauvegarde des droits de homme et des libertés fondamentales. </p>
<p>SECOND MOYEN DE CASSATION </p>
<p>Il est fait grief à arrêt attaqué avoir confirmé le jugement entrepris en ce qu'il avait condamné la société Culture Press aux dépens et au paiement de frais irrépétibles au profit de Boris C...et avoir condamné la société Culture Press aux dépens appel et au paiement de frais irrépétibles au profit du même Boris C..., </p>
<p>AUX MOTIFS, ADOPTES DES PREMIERS JUGES, QU'aucune considération équité ne commande de faire application de article 700 du code de procédure civile à autres parties que les demandeurs ; </p>
<p>ET AUX MOTIFS PROPRES QUE équité commande de condamner la société Culture Press à verser à chacun des demandeurs la somme de 1. 500 euros au titre des frais irrépétibles exposés en cause appel ; </p>
<p>ALORS QUE la partie perdante est condamnée aux dépens, à moins que le juge, par décision motivée, n'en mette la totalité ou une fraction à la charge une autre partie ; que le juge condamne la partie tenue aux dépens ou, à défaut, la partie perdante, à payer à autre partie la somme qu'il détermine, au titre des frais exposés et non compris dans les dépens ; qu'il en déduit que la condamnation de la partie qui n'a pas succombé aux dépens et au paiement des frais irrépétibles doit être assortie une motivation spéciale ; qu'en condamnant la société Culture Press, au profit de M. C..., aux dépens et frais irrépétibles de première instance et appel, sans assortir sa décision une motivation spéciale, bien que Boris C...ait été débouté de toutes ses demandes à encontre de la société Culture Press, la cour appel a violé les articles 696 et 700 du code de procédure civile.</p>

</CONTENU>
</BLOC_TEXTUEL>
<SOMMAIRE>
<SCT ID="1" TYPE="PRINCIPAL">CONFLIT DE LOIS - Propriété littéraire et artistique -  Droits voisins du droit auteur -  Droits des artistes-interprètes -  Titulaire initial -  Détermination -  Loi applicable -  Loi du pays où la protection est réclamée
</SCT>
<SCT ID="1" TYPE="REFERENCE">PROPRIETE LITTERAIRE ET ARTISTIQUE -  Droits voisins du droit auteur -  Droits des artistes-interprètes -  Titulaire initial -  Détermination -  Loi applicable -  Loi du pays où la protection est réclamée
</SCT>
<ANA ID="1">La règle de conflit de lois applicable à la détermination du titulaire initial des droits artiste-interprète et de producteur de phonogrammes désigne la loi du pays où la protection est réclamée</ANA>
</SOMMAIRE>

<CITATION_JP>
<CONTENU>Dans le même sens que :1re Civ., 19 juin 2013, pourvoi n° 12-18.032, Bull. 2013, I, n° 128 (rejet)



</CONTENU>
</CITATION_JP>
</TEXTE>
<LIENS>
<LIEN cidtexte="" datesignatexte="" id="" naturetexte="" nortexte="" num="" numtexte="" sens="source" typelien="CITATION">Convention de Rome du 26 octobre 1961 ; article L. 212-3 du code de la propriété intellectuelle</LIEN>
</LIENS>
</TEXTE_JURI_JUDI>
